pgp_reconstruction/__init__.py
pgp_reconstruction/config.cfg
pgp_reconstruction/cli/download_missing_data.py
pgp_reconstruction/cli/pgprec.py
pgp_reconstruction/cli/util.py
pgp_reconstruction/data/generated/README.md
pgp_reconstruction/data/input/README.md
pgp_reconstruction/dependencies/README.md
pgp_reconstruction/reconstruction/diamond.py
pgp_reconstruction/reconstruction/findOrfs.py
pgp_reconstruction/reconstruction/findSoftConstraints.py
pgp_reconstruction/reconstruction/makeEssentialRxns.py
pgp_reconstruction/reconstruction/prune_universal_model.py
pgp_reconstruction/reconstruction/scoring.py
pgp_reconstruction-0.0.6.1.dist-info/LICENSE.md
pgp_reconstruction-0.0.6.1.dist-info/METADATA
pgp_reconstruction-0.0.6.1.dist-info/WHEEL
pgp_reconstruction-0.0.6.1.dist-info/top_level.txt
pgp_reconstruction-0.0.6.1.dist-info/RECORD
