Metadata-Version: 2.1
Name: pgp-reconstruction
Version: 0.0.6.1
Summary: Pathway-Guided Pruning Reconstruction of constraint-based metabolic models
Author: rcolpo (Rodrigo Amarante Colpo)
Author-email: <rodrigocolpo@gmail.com>
License: Apache Software License 2.0
Keywords: python,carveme,PGP Reconstruction,gapseq
Classifier: Development Status :: 2 - Pre-Alpha
Classifier: Environment :: Console
Classifier: Intended Audience :: Science/Research
Classifier: Topic :: Scientific/Engineering :: Bio-Informatics
Classifier: Programming Language :: Python :: 3
Classifier: License :: OSI Approved :: Apache Software License
License-File: LICENSE.md
Requires-Dist: reframed >=1.2.1
Requires-Dist: pandas >=1.0
Requires-Dist: cobra
